src/__init__.py
src/cli.py
src/func/__init__.py
src/func/deploy.py
src/repo/__init__.py
src/repo/create.py
src/storage/__init__.py
src/storage/buckets.py
src/storage/files.py
src/storage/helpers.py
tal-0.0.6.dist-info/LICENSE
tal-0.0.6.dist-info/METADATA
tal-0.0.6.dist-info/WHEEL
tal-0.0.6.dist-info/entry_points.txt
tal-0.0.6.dist-info/top_level.txt
tal-0.0.6.dist-info/RECORD
