Metadata-Version: 2.1
Name: tal
Version: 0.0.6
Summary: Build Tool
Home-page: https://github.com/woodpav/tal
Author: Ty Wood-Pavicich
Author-email: devwoodpav@gmail.com
License: UNKNOWN
Platform: UNKNOWN
